rssfeed-0.4.1.dist-info/METADATA
rssfeed-0.4.1.dist-info/WHEEL
rssfeed-0.4.1.dist-info/entry_points.txt
rssfeed-0.4.1.dist-info/licenses/LICENSE
rssfeed/__init__.py
rssfeed/lib.py
rssfeed-0.4.1.dist-info/RECORD
