Metadata-Version: 2.1
Name: rssfeed
Version: 0.4.1
Summary: A simple rss/atom feed parser
Keywords: rssfeed,rss,feed,atom,opml
Author: p7e4
License: GPLv3
Classifier: Programming Language :: Python :: 3
Classifier: Programming Language :: Python :: 3.12
Classifier: Programming Language :: Python :: 3.13
Classifier: License :: OSI Approved :: GNU General Public License v3 (GPLv3)
Classifier: Topic :: Text Processing :: Markup :: XML
Project-URL: Repository, https://github.com/p7e4/rssfeed
Project-URL: Issues, https://github.com/p7e4/rssfeed/issues
Requires-Python: >=3.12
Requires-Dist: python-dateutil>=2.9
